{
  "sections": {
    "96005cb7-8e74-4a78-aa83-708fca123576": {
      "type": "slideshow",
      "blocks": {
        "template--18349128974636__96005cb7-8e74-4a78-aa83-708fca123576-16789992695e16444c-0": {
          "type": "slide",
          "settings": {
            "image": "shopify:\/\/shop_images\/ph_design-timeline.jpg",
            "heading": "Creating comfort",
            "heading_size": "h1",
            "subheading": "since 2010",
            "button_label": "",
            "link": "",
            "button_style_secondary": false,
            "box_align": "middle-center",
            "show_text_box": true,
            "text_alignment": "center",
            "image_overlay_opacity": 0,
            "color_scheme": "background-1",
            "text_alignment_mobile": "center"
          }
        },
        "template--18349128974636__96005cb7-8e74-4a78-aa83-708fca123576-16789992695e16444c-1": {
          "type": "slide",
          "settings": {
            "image": "shopify:\/\/shop_images\/pexels-tome-louro-1666779.jpg",
            "heading": "",
            "heading_size": "h1",
            "subheading": "",
            "button_label": "",
            "link": "",
            "button_style_secondary": false,
            "box_align": "middle-center",
            "show_text_box": false,
            "text_alignment": "center",
            "image_overlay_opacity": 0,
            "color_scheme": "background-1",
            "text_alignment_mobile": "center"
          }
        },
        "e76e4e9a-38ba-458a-a216-feaf75425f7f": {
          "type": "slide",
          "settings": {
            "image": "shopify:\/\/shop_images\/pexels-mariam-antadze-15878388.jpg",
            "heading": "",
            "heading_size": "h1",
            "subheading": "",
            "button_label": "",
            "link": "",
            "button_style_secondary": false,
            "box_align": "middle-center",
            "show_text_box": false,
            "text_alignment": "center",
            "image_overlay_opacity": 0,
            "color_scheme": "background-1",
            "text_alignment_mobile": "center"
          }
        }
      },
      "block_order": [
        "template--18349128974636__96005cb7-8e74-4a78-aa83-708fca123576-16789992695e16444c-0",
        "template--18349128974636__96005cb7-8e74-4a78-aa83-708fca123576-16789992695e16444c-1",
        "e76e4e9a-38ba-458a-a216-feaf75425f7f"
      ],
      "settings": {
        "layout": "full_bleed",
        "slide_height": "medium",
        "slider_visual": "counter",
        "auto_rotate": false,
        "change_slides_speed": 5,
        "show_text_below": true,
        "accessibility_info": "Slideshow about our brand"
      }
    },
    "231ab799-bc4e-4768-be5e-90ce840c39db": {
      "type": "featured-product",
      "blocks": {
        "template--18349128974636__231ab799-bc4e-4768-be5e-90ce840c39db-167893537460216507-0": {
          "type": "text",
          "settings": {
            "text": "",
            "text_style": "uppercase"
          }
        },
        "template--18349128974636__231ab799-bc4e-4768-be5e-90ce840c39db-167893537460216507-1": {
          "type": "title",
          "settings": {
            "heading_size": "h1"
          }
        },
        "template--18349128974636__231ab799-bc4e-4768-be5e-90ce840c39db-167893537460216507-2": {
          "type": "price",
          "settings": {
          }
        },
        "template--18349128974636__231ab799-bc4e-4768-be5e-90ce840c39db-167893537460216507-3": {
          "type": "variant_picker",
          "settings": {
            "picker_type": "button"
          }
        },
        "template--18349128974636__231ab799-bc4e-4768-be5e-90ce840c39db-167893537460216507-4": {
          "type": "quantity_selector",
          "settings": {
          }
        },
        "template--18349128974636__231ab799-bc4e-4768-be5e-90ce840c39db-167893537460216507-5": {
          "type": "buy_buttons",
          "settings": {
            "show_dynamic_checkout": true
          }
        },
        "d3c569bb-7346-4e76-952d-e151e93b492f": {
          "type": "custom_liquid",
          "settings": {
            "custom_liquid": "{% if product.metafields.custom.care_instructions %}\n                <div class=\"metafield-care-instructions-container\">\n                  {% for metafield in product.metafields.custom.care_instructions.value %}\n\n                    <div class=\"metafield-care-instructions\">\n                      {% comment %} Check metafield name and display corresponding image {% endcomment %}\n                      {% if metafield == \"Wash On Cold\" %}\n                      <img class=\"metafield-care-instructions-image\" src=\"{{ 'Wash_On_Cold.jpg' | file_img_url: '2048x2048' }}\" \/>\n                      {% elsif metafield == \"Do Not Use Softener\" %}\n                      <img class=\"metafield-care-instructions-image\" src=\"{{ 'Do_Not_Use_Softener.jpg' | file_img_url: '2048x2048' }}\" \/>\n                      {% elsif metafield == \"Wash and Iron Inside Out\" %}\n                      <img class=\"metafield-care-instructions-image\" src=\"{{ 'Wash_And_Iron_Inside_Out.jpg' | file_img_url: '2048x2048' }}\" \/>\n                      {% elsif metafield == \"Iron\" %}\n                      <img class=\"metafield-care-instructions-image\" src=\"{{ 'Iron.jpg' | file_img_url: '2048x2048' }}\" \/>\n                      {% elsif metafield == \"Hang To Dry\" %}\n                      <img class=\"metafield-care-instructions-image\" src=\"{{ 'Hang_To_Dry.jpg' | file_img_url: '2048x2048' }}\" \/>\n                      {% elsif metafield == \"Do Not Handwash\" %}\n                      <img class=\"metafield-care-instructions-image\" src=\"{{ 'Do_Not_Hand_Wash.jpg' | file_img_url: '2048x2048' }}\" \/>\n                      {% elsif metafield == \"Do Not Dry Clean\" %}\n                      <img class=\"metafield-care-instructions-image\" src=\"{{ 'Do_Not_Dry_Clean.jpg' | file_img_url: '2048x2048' }}\" \/>\n                      {% elsif metafield == \"Wash With Lights\" %}\n                      <img class=\"metafield-care-instructions-image\" src=\"{{ 'Wash_With_Lights.jpg' | file_img_url: '2048x2048' }}\" \/>\n                      {% endif %}\n\n                      <p class=\"metafield-care-instructions text\">{{ metafield }}<\/p>\n                    <\/div>\n                  {% endfor %}\n                <\/div>\n              {% endif %}"
          }
        },
        "template--18349128974636__231ab799-bc4e-4768-be5e-90ce840c39db-167893537460216507-6": {
          "type": "share",
          "settings": {
            "share_label": "Share"
          }
        },
        "4fc56088-8d59-4a87-acca-605f8dab4af6": {
          "type": "care_guide",
          "settings": {
          }
        }
      },
      "block_order": [
        "template--18349128974636__231ab799-bc4e-4768-be5e-90ce840c39db-167893537460216507-0",
        "template--18349128974636__231ab799-bc4e-4768-be5e-90ce840c39db-167893537460216507-1",
        "template--18349128974636__231ab799-bc4e-4768-be5e-90ce840c39db-167893537460216507-2",
        "template--18349128974636__231ab799-bc4e-4768-be5e-90ce840c39db-167893537460216507-3",
        "template--18349128974636__231ab799-bc4e-4768-be5e-90ce840c39db-167893537460216507-4",
        "template--18349128974636__231ab799-bc4e-4768-be5e-90ce840c39db-167893537460216507-5",
        "d3c569bb-7346-4e76-952d-e151e93b492f",
        "template--18349128974636__231ab799-bc4e-4768-be5e-90ce840c39db-167893537460216507-6",
        "4fc56088-8d59-4a87-acca-605f8dab4af6"
      ],
      "settings": {
        "product": "tie-dye-hoodie",
        "color_scheme": "background-2",
        "secondary_background": false,
        "media_size": "medium",
        "constrain_to_viewport": true,
        "media_fit": "contain",
        "media_position": "left",
        "image_zoom": "lightbox",
        "hide_variants": false,
        "enable_video_looping": false,
        "padding_top": 36,
        "padding_bottom": 36
      }
    },
    "c191d720-e046-40e1-b46f-628e12fab498": {
      "type": "image-with-text",
      "blocks": {
        "template--18349128974636__c191d720-e046-40e1-b46f-628e12fab498-1678998681708b6746-0": {
          "type": "heading",
          "settings": {
            "heading": "About us",
            "heading_size": "h1"
          }
        },
        "template--18349128974636__c191d720-e046-40e1-b46f-628e12fab498-1678998681708b6746-1": {
          "type": "text",
          "settings": {
            "text": "<p>Panda Hoodies was founded in 2010 by a group of friends who shared a passion for cute and comfortable clothing. They noticed a gap in the market for high-quality hoodies featuring panda designs, which they believed would appeal to a wide range of customers.<\/p><p>In 2015, Panda Hoodies launched their first international online store, which allowed them to reach customers all over the world. They also began to offer other clothing items featuring panda designs, such as t-shirts and leggings.<\/p><p>Today, Panda Hoodies is a well-known brand in the fashion industry, with a strong online presence and a loyal customer base. The company continues to innovate and expand their product line while maintaining their commitment to quality and customer satisfaction.<\/p>",
            "text_style": "body"
          }
        }
      },
      "block_order": [
        "template--18349128974636__c191d720-e046-40e1-b46f-628e12fab498-1678998681708b6746-0",
        "template--18349128974636__c191d720-e046-40e1-b46f-628e12fab498-1678998681708b6746-1"
      ],
      "settings": {
        "section_id": "about-us",
        "image": "shopify:\/\/shop_images\/pexels-phillip-pfeiffer-2407600.jpg",
        "height": "adapt",
        "desktop_image_width": "medium",
        "layout": "text_first",
        "desktop_content_position": "top",
        "desktop_content_alignment": "left",
        "content_layout": "no-overlap",
        "color_scheme": "background-1",
        "mobile_content_alignment": "left",
        "padding_top": 36,
        "padding_bottom": 36
      }
    },
    "c7a21860-6e4f-4b9d-bb87-c71b46162382": {
      "type": "contact-form",
      "settings": {
        "heading": "Contact form",
        "heading_size": "h1",
        "color_scheme": "background-2",
        "padding_top": 36,
        "padding_bottom": 36
      }
    },
    "e1ce87fa-f4e8-472c-8ad7-3fd87c782a6d": {
      "type": "store-locator",
      "blocks": {
        "42e97c1e-bb8f-4338-bb26-2e5bdc39298d": {
          "type": "single-location",
          "settings": {
            "address": "123 Fake St",
            "hours": "9am-5pm Monday to Sunday",
            "maps-link": "https:\/\/www.google.com\/maps\/embed?pb=!1m18!1m12!1m3!1d92823.86575698238!2d-79.6074903428608!3d43.76349345574679!2m3!1f0!2f0!3f0!3m2!1i1024!2i768!4f13.1!3m3!1m2!1s0x882b3b78887572cf%3A0xc2bd8fb5ca162f85!2s7855%20Finch%20Ave%20W%2C%20Brampton%2C%20ON%20L6T%200B2!5e0!3m2!1sen!2sca!4v1679017749378!5m2!1sen!2sca"
          }
        },
        "4be7f835-d646-43b8-b58d-80d18bbef4e3": {
          "type": "single-location",
          "settings": {
            "address": "226 Fake St",
            "hours": "2-8pm Wednesdays",
            "maps-link": "https:\/\/www.google.com\/maps\/embed?pb=!1m18!1m12!1m3!1d19249.034334555115!2d-79.5342832195093!3d43.77221949456904!2m3!1f0!2f0!3f0!3m2!1i1024!2i768!4f13.1!3m3!1m2!1s0x882b2fd0515f365b%3A0xd751ee997420d7d!2s4001%20Steeles%20Ave%20W%2C%20North%20York%2C%20ON%20M3N%202T8!5e0!3m2!1sen!2sca!4v1679024107231!5m2!1sen!2sca"
          }
        },
        "8dcb7a7a-03e5-4379-95cc-e8d475aa7593": {
          "type": "single-location",
          "settings": {
            "address": "456 Real St",
            "hours": "9am-5pm Monday to Friday",
            "maps-link": "https:\/\/www.google.com\/maps\/embed?pb=!1m18!1m12!1m3!1d27226.45407529732!2d-79.57449487536314!3d43.6022267986609!2m3!1f0!2f0!3f0!3m2!1i1024!2i768!4f13.1!3m3!1m2!1s0x882b4876b0587f71%3A0x2c8fe90ae88c8b9b!2s1305%20Dixie%20Rd%2C%20Mississauga%2C%20ON%20L5E%202P5!5e0!3m2!1sen!2sca!4v1679028404749!5m2!1sen!2sca"
          }
        },
        "7f51a62c-77f0-48fd-9194-581a3dd2389b": {
          "type": "single-location",
          "settings": {
            "address": "Scarborough",
            "hours": "Open sometimes, closed sometimes",
            "maps-link": "https:\/\/www.google.com\/maps\/embed?pb=!1m18!1m12!1m3!1d38086.03647810737!2d-79.27142594683508!3d43.84043880586352!2m3!1f0!2f0!3f0!3m2!1i1024!2i768!4f13.1!3m3!1m2!1s0x89d4d71a399d3525%3A0xd5aa90e932d8d3e!2s6415%20Steeles%20Ave%20E%2C%20Scarborough%2C%20ON%20M1X%201N5!5e0!3m2!1sen!2sca!4v1679028456350!5m2!1sen!2sca"
          }
        }
      },
      "block_order": [
        "42e97c1e-bb8f-4338-bb26-2e5bdc39298d",
        "4be7f835-d646-43b8-b58d-80d18bbef4e3",
        "8dcb7a7a-03e5-4379-95cc-e8d475aa7593",
        "7f51a62c-77f0-48fd-9194-581a3dd2389b"
      ],
      "settings": {
        "heading": "Store Locator"
      }
    }
  },
  "order": [
    "96005cb7-8e74-4a78-aa83-708fca123576",
    "231ab799-bc4e-4768-be5e-90ce840c39db",
    "c191d720-e046-40e1-b46f-628e12fab498",
    "c7a21860-6e4f-4b9d-bb87-c71b46162382",
    "e1ce87fa-f4e8-472c-8ad7-3fd87c782a6d"
  ]
}
